vedro_playwright/__init__.py
vedro_playwright/_browser_engine.py
vedro_playwright/_browser_registry.py
vedro_playwright/_browsers.py
vedro_playwright/_screenshot_path.py
vedro_playwright/_screenshots_mode.py
vedro_playwright/_vedro_playwright.py
vedro_playwright/py.typed
vedro_playwright-1.2.1.dist-info/LICENSE
vedro_playwright-1.2.1.dist-info/METADATA
vedro_playwright-1.2.1.dist-info/WHEEL
vedro_playwright-1.2.1.dist-info/top_level.txt
vedro_playwright-1.2.1.dist-info/RECORD
