Metadata-Version: 2.1
Name: vedro-playwright
Version: 1.2.1
Summary: Vedro + playwright
Home-page: https://github.com/artkuznetsov/vedro-playwright
Author: artkuznetsov
Author-email: kuznets.a.g@gmail.com
License: Apache-2.0
Classifier: License :: OSI Approved :: Apache Software License
Classifier: Programming Language :: Python :: 3.8
Classifier: Programming Language :: Python :: 3.9
Classifier: Programming Language :: Python :: 3.10
Classifier: Typing :: Typed
Requires-Python: >=3.8
License-File: LICENSE
Requires-Dist: vedro (<2.0,>=1.7)
Requires-Dist: playwright (<2.0,>=1.21)
